libretro_scummvm_playlist/__init__.py
libretro_scummvm_playlist/__main__.py
libretro_scummvm_playlist-2.5.3.dist-info/entry_points.txt
libretro_scummvm_playlist-2.5.3.dist-info/LICENSE
libretro_scummvm_playlist-2.5.3.dist-info/WHEEL
libretro_scummvm_playlist-2.5.3.dist-info/METADATA
libretro_scummvm_playlist-2.5.3.dist-info/RECORD
